Workbook

Sheet Calculadora CAPM
A1: Calculadora de CAPM (con Riesgo País)
A2: Evaluación de Proyectos de Tecnología, UADE
A4: Celdas amarillas: editar. Celdas blancas: fórmulas, no tocar.
A6: Dato | B6: Valor | D6: Notas y fuentes
A7: Tasa libre de riesgo (rf) | B7: 0.0472 | D7: rf: rendimiento del bono del Tesoro de EE.UU. a 10 años. Fuente: FRED, serie DGS10, fred.stlouisfed.org/series/DGS10. β: dataset Global de Aswath Damodaran (Stern School of Business), categoría 'Computer Services'. Se actualiza en enero de cada año. RP: riesgo país argentino EMBI+ de JP Morgan, en puntos básicos dividido 10.000 para pasarlo a porcentaje. Fuente: Ámbito Financiero, ambito.com/contenidos/riesgo-pais.html. rf y RP son datos de mercado que cambian todos los días: actualizarlos antes de cada clase.
A8: Rentabilidad esperada del mercado (E(rm)) | B8: 0.09
A9: Beta sectorial (β) | B9: 1.12
A10: Riesgo país (RP) | B10: 0.0505
A12: Resultado | B12: Valor
A13: Prima de mercado: E(rm) - rf | B13: =B8-B7 -> 0.0428
A14: Prima ajustada por beta: β × [E(rm)-rf] | B14: =B9*B13 -> 0.047936
A15: E(ri) = rf + prima ajustada + RP | B15: =B7+B14+B10 -> 0.145636

Sheet Sensibilidad CAPM
A1: Sensibilidad de E(ri) según el Riesgo País
A2: Mantiene fijos rf, E(rm) y beta de la hoja anterior y varía el Riesgo País para mostrar el impacto real del contexto macroeconómico argentino sobre la tasa exigida al proyecto.
A4: Riesgo País (RP) | B4: En puntos básicos | C4: E(ri)
A5: 0 | B5: 0 | C5: ='Calculadora CAPM'!$B$7+'Calculadora CAPM'!$B$14+A5 -> 0.095136
A6: 0.02 | B6: 200 | C6: ='Calculadora CAPM'!$B$7+'Calculadora CAPM'!$B$14+A6 -> 0.115136
A7: 0.04 | B7: 400 | C7: ='Calculadora CAPM'!$B$7+'Calculadora CAPM'!$B$14+A7 -> 0.135136
A8: 0.0505 | B8: 505 | C8: ='Calculadora CAPM'!$B$7+'Calculadora CAPM'!$B$14+A8 -> 0.145636
A9: 0.06 | B9: 600 | C9: ='Calculadora CAPM'!$B$7+'Calculadora CAPM'!$B$14+A9 -> 0.155136
A10: 0.08 | B10: 800 | C10: ='Calculadora CAPM'!$B$7+'Calculadora CAPM'!$B$14+A10 -> 0.175136
A11: 0.1 | B11: 1000 | C11: ='Calculadora CAPM'!$B$7+'Calculadora CAPM'!$B$14+A11 -> 0.195136
A12: 0.12 | B12: 1200 | C12: ='Calculadora CAPM'!$B$7+'Calculadora CAPM'!$B$14+A12 -> 0.215136
A13: 0.15 | B13: 1500 | C13: ='Calculadora CAPM'!$B$7+'Calculadora CAPM'!$B$14+A13 -> 0.245136
A14: 0.18 | B14: 1800 | C14: ='Calculadora CAPM'!$B$7+'Calculadora CAPM'!$B$14+A14 -> 0.275136
A15: 0.2 | B15: 2000 | C15: ='Calculadora CAPM'!$B$7+'Calculadora CAPM'!$B$14+A15 -> 0.295136
A16: Para usar otro escenario, cambiá rf, E(rm) o beta en la hoja 'Calculadora CAPM': esta tabla se recalcula sola.

Sheet Ejercitación
A1: Ejercitación: el mismo Ke, dos maneras de llegar a él
A2: Es la misma empresa de desarrollo de software de la Ejercitación 2 (WACC). Ahí el Ke = 24% vino dado como un dato del enunciado. Acá lo van a estimar con CAPM, para compararlo contra ese dato y ver qué cambia en el WACC si lo reemplazan.
A4: Dato del enunciado | B4: Valor | D4: Tareas a resolver
A5: Tasa libre de riesgo (rf) | B5: 0.043 | D5: 1. Completar RP con el dato del día y calcular E(ri). 2. Comparar el resultado con el WACC calculado en la Ejercitación anterior (ver el otro archivo, EPT_Clase5_MatematicaFinancieraIII_Calculadora_WACC.xlsx). 3. Análisis crítico: si ambas tasas estuvieran disponibles para el mismo proyecto, ¿cuál usarían y por qué?
A6: Rentabilidad del mercado (E(rm)) | B6: 0.085
A7: Beta (β), sector Computer Services (misma empresa de software) | B7: 1.12
A8: Riesgo país (RP), completar con el dato del día | B8: 0.049
A10: Resultado | B10: Valor
A11: Prima de mercado: E(rm) - rf | B11: =B6-B5 -> 0.042
A12: Prima ajustada por beta: β × [E(rm)-rf] | B12: =B7*B11 -> 0.04704
A13: E(ri) | B13: =B5+B12+B8 -> 0.13904
A15: Paso 2: comparar contra el Ke asumido en WACC | B15: Valor
A16: Ke asumido en el enunciado de la Ejercitación 2 (dato a comparar) | B16: 0.24
A17: Diferencia: E(ri) calculado menos Ke asumido | B17: =B13-B16 -> -0.10096
A19: Paso 3: recalcular el WACC con este nuevo Ke | B19: Valor
A20: Deuda bancaria (% del total, igual que en la Ejercitación 2) | B20: 0.3
A21: Capital propio (% del total, igual que en la Ejercitación 2) | B21: 0.7
A22: Tasa de interés bancaria, Tp (igual que en la Ejercitación 2) | B22: 0.18
A23: Impuesto a las ganancias, t (igual que en la Ejercitación 2) | B23: 0.35
A24: Kp = Tp × (1 - t) | B24: =B22*(1-B23) -> 0.117
A25: Deuda ponderada: %Deuda × Kp | B25: =B20*B24 -> 0.0351
A26: Capital ponderado ORIGINAL: %Capital × Ke asumido (24%) | B26: =B21*B16 -> 0.168
A27: Capital ponderado NUEVO: %Capital × E(ri) calculado con CAPM | B27: =B21*B13 -> 0.097328
A28: WACC ORIGINAL (con Ke = 24% asumido) | B28: =B25+B26 -> 0.2031
A29: WACC NUEVO (con el Ke que salió de CAPM) | B29: =B25+B27 -> 0.132428
A30: Diferencia entre el WACC nuevo y el original | B30: =B29-B28 -> -0.070672
A32: Si el WACC nuevo y el original quedan parecidos, el Ke asumido en la Ejercitación 2 era una estimación razonable. Si quedan muy distintos, es la evidencia concreta de qué tanto puede cambiar la decisión de un proyecto según de dónde saques el Ke.
