Workbook

Sheet Calculadora WACC
A1: Calculadora de WACC
A2: Evaluación de Proyectos de Tecnología, UADE
A4: Celdas amarillas: editar. Celdas blancas: fórmulas, no tocar.
A6: Dato | B6: Valor | D6: Notas
A7: Deuda (D) | B7: 80 | D7: Los valores precargados son el ejemplo numérico de la clase: Activo $100 financiado con Deuda $80 y Patrimonio Neto $20 Ke = 27% Kd = 20% t = 35%. WACC esperado: 15,8%.
A8: Patrimonio Neto o Capital propio (PN) | B8: 20
A9: Tasa exigida por accionistas (Ke) | B9: 0.27
A10: Tasa de la deuda antes de impuestos (Kd) | B10: 0.2
A11: Tasa de impuesto a las ganancias (t) | B11: 0.35
A14: Resultado | B14: Valor | D14: Fórmula usada
A15: Costo de la deuda neto de impuestos (Kp = Kd × (1-t)) | B15: =B10*(1-B11) -> 0.13
A16: Peso de la Deuda: D / (D+PN) | B16: =B7/(B7+B8) -> 0.8
A17: Peso del Capital propio: PN / (D+PN) | B17: =B8/(B7+B8) -> 0.2
A18: Deuda ponderada: peso D × Kp | B18: =B16*B15 -> 0.104
A19: Capital ponderado: peso PN × Ke | B19: =B17*B9 -> 0.054
A20: WACC | B20: =B18+B19 -> 0.158

Sheet Sensibilidad WACC
A1: Sensibilidad del WACC según proporción de Deuda
A2: Mantiene fijas Ke, Kd y t de la hoja anterior y varía el peso de la Deuda de 0% a 100% para mostrar el efecto del apalancamiento sobre el WACC.
A4: % Deuda sobre el total | B4: % Capital propio | C4: Deuda ponderada | D4: Capital ponderado | E4: WACC
A5: 0 | B5: =1-A5 -> 1 | C5: =A5*'Calculadora WACC'!$B$15 -> 0 | D5: =B5*'Calculadora WACC'!$B$9 -> 0.27 | E5: =C5+D5 -> 0.27
A6: 0.1 | B6: =1-A6 -> 0.9 | C6: =A6*'Calculadora WACC'!$B$15 -> 0.013 | D6: =B6*'Calculadora WACC'!$B$9 -> 0.243 | E6: =C6+D6 -> 0.256
A7: 0.2 | B7: =1-A7 -> 0.8 | C7: =A7*'Calculadora WACC'!$B$15 -> 0.026 | D7: =B7*'Calculadora WACC'!$B$9 -> 0.216 | E7: =C7+D7 -> 0.242
A8: 0.3 | B8: =1-A8 -> 0.7 | C8: =A8*'Calculadora WACC'!$B$15 -> 0.039 | D8: =B8*'Calculadora WACC'!$B$9 -> 0.189 | E8: =C8+D8 -> 0.228
A9: 0.4 | B9: =1-A9 -> 0.6 | C9: =A9*'Calculadora WACC'!$B$15 -> 0.052 | D9: =B9*'Calculadora WACC'!$B$9 -> 0.162 | E9: =C9+D9 -> 0.214
A10: 0.5 | B10: =1-A10 -> 0.5 | C10: =A10*'Calculadora WACC'!$B$15 -> 0.065 | D10: =B10*'Calculadora WACC'!$B$9 -> 0.135 | E10: =C10+D10 -> 0.2
A11: 0.6 | B11: =1-A11 -> 0.4 | C11: =A11*'Calculadora WACC'!$B$15 -> 0.078 | D11: =B11*'Calculadora WACC'!$B$9 -> 0.108 | E11: =C11+D11 -> 0.186
A12: 0.7 | B12: =1-A12 -> 0.3 | C12: =A12*'Calculadora WACC'!$B$15 -> 0.091 | D12: =B12*'Calculadora WACC'!$B$9 -> 0.081 | E12: =C12+D12 -> 0.172
A13: 0.8 | B13: =1-A13 -> 0.2 | C13: =A13*'Calculadora WACC'!$B$15 -> 0.104 | D13: =B13*'Calculadora WACC'!$B$9 -> 0.054 | E13: =C13+D13 -> 0.158
A14: 0.9 | B14: =1-A14 -> 0.1 | C14: =A14*'Calculadora WACC'!$B$15 -> 0.117 | D14: =B14*'Calculadora WACC'!$B$9 -> 0.027 | E14: =C14+D14 -> 0.144
A15: 1 | B15: =1-A15 -> 0 | C15: =A15*'Calculadora WACC'!$B$15 -> 0.13 | D15: =B15*'Calculadora WACC'!$B$9 -> 0 | E15: =C15+D15 -> 0.13
A16: Para usar otro escenario, cambiá Ke, Kd o t en la hoja 'Calculadora WACC': esta tabla se recalcula sola.

Sheet Ejercitación
A1: Ejercitación: empresa de desarrollo de software
A2: Una empresa de desarrollo de software requiere evaluar el costo de su estructura de capital para la toma de decisiones estratégicas de inversión.
A4: Dato del enunciado | B4: Valor | D4: Consignas
A5: Valor total del Activo | B5: 250000 | D5: 1. Calcular el costo de la deuda neto de efectos impositivos (Kp). 2. Aplicar la fórmula del WACC ponderando ambas fuentes de financiamiento.
A6: Deuda bancaria (% del total) | B6: 0.3
A7: Capital propio (% del total) | B7: 0.7
A8: Rendimiento de accionistas (Ke) | B8: 0.24
A9: Tasa de interés bancaria (Tp) | B9: 0.18
A10: Impuesto a las ganancias (Tiigg) | B10: 0.35
A12: Paso 1: costo de la deuda neto de impuestos | B12: Valor
A13: Kp = Tp × (1 - Tiigg) | B13: =B9*(1-B10) -> 0.117
A15: Paso 2: ponderación | B15: Valor
A16: Deuda ponderada: %Deuda × Kp | B16: =B6*B13 -> 0.0351
A17: Capital ponderado: %Capital × Ke | B17: =B7*B8 -> 0.168
A19: Resultado | B19: Valor
A20: WACC | B20: =B16+B17 -> 0.2031
